tot_cmd/__init__.py
tot_cmd/cmd.py
tot_cmd-0.3.9.dist-info/METADATA
tot_cmd-0.3.9.dist-info/WHEEL
tot_cmd-0.3.9.dist-info/entry_points.txt
tot_cmd-0.3.9.dist-info/top_level.txt
tot_cmd-0.3.9.dist-info/RECORD
