Metadata-Version: 2.1
Name: tot_cmd
Version: 0.3.9
Summary: Default template for PDM package
Author-email: EstherCho-7 <dkgkqm777@gmail.com>
License: MIT
Project-URL: Homepage, https://github.com/EstherCho-7/tot_cmd
Project-URL: Issues, https://github.com/EstherCho-7/tot_cmd/issues
Requires-Python: >=3.9
Requires-Dist: tot-plus >=0.2.2
Requires-Dist: tot-minus >=0.1.3
Requires-Dist: tot-multi >=0.1.1
